scan_merge.py
scan_merge-1.1.dist-info/COPYING.md
scan_merge-1.1.dist-info/METADATA
scan_merge-1.1.dist-info/WHEEL
scan_merge-1.1.dist-info/entry_points.txt
scan_merge-1.1.dist-info/top_level.txt
scan_merge-1.1.dist-info/RECORD
