Metadata-Version: 2.1
Name: scan_merge
Version: 1.1
Summary: Tool to merge scanned PDFs from single sided document feeders
Author-email: Arvid Norlander <VorpalBlade@users.noreply.github.com>
License: GPL-3.0
Project-URL: Source, https://github.com/VorpalBlade/scan_merge
Classifier: Development Status :: 4 - Beta
Classifier: Environment :: Console
Classifier: Intended Audience :: End Users/Desktop
Classifier: License :: OSI Approved :: GNU General Public License v3 (GPLv3)
Classifier: Programming Language :: Python :: 3 :: Only
Classifier: Programming Language :: Python :: 3.7
Classifier: Topic :: Multimedia :: Graphics :: Capture :: Scanners
License-File: COPYING.md
Requires-Dist: argcomplete
Requires-Dist: funcy
Requires-Dist: pypdf2 >=3.0
